sparsedlist.py
sparsedlist-0.4.dist-info/METADATA
sparsedlist-0.4.dist-info/RECORD
sparsedlist-0.4.dist-info/WHEEL
sparsedlist-0.4.dist-info/top_level.txt
