Metadata-Version: 2.1
Name: sparsedlist
Version: 0.4
Summary: Endless list with non-contiguous indexes
Home-page: https://github.com/bdragon300/sparsedlist
Author: Igor Derkach
Author-email: gosha753951@gmail.com
License: Apache-2.0
Platform: UNKNOWN
Classifier: Programming Language :: Python :: 3
Classifier: Development Status :: 5 - Production/Stable
Classifier: License :: OSI Approved :: Apache Software License
Classifier: Operating System :: POSIX
Classifier: Operating System :: Microsoft :: Windows
Classifier: Operating System :: MacOS
Classifier: Topic :: Software Development :: Libraries :: Python Modules
Requires-Dist: pyskiplist
